pyflies/__init__.py
pyflies/components.py
pyflies/evaluated.py
pyflies/exceptions.py
pyflies/scope.py
pyflies/table.py
pyflies/time.py
pyflies/tools.py
pyflies/components/audio.pfc
pyflies/components/base.pfc
pyflies/components/circle.pfc
pyflies/components/cross.pfc
pyflies/components/image.pfc
pyflies/components/keyboard.pfc
pyflies/components/line.pfc
pyflies/components/mouse.pfc
pyflies/components/rectangle.pfc
pyflies/components/sound.pfc
pyflies/components/text.pfc
pyflies/generators/__init__.py
pyflies/generators/csv/__init__.py
pyflies/generators/csv/csv.jinja
pyflies/generators/log/__init__.py
pyflies/generators/log/debug.log.jinja
pyflies/lang/__init__.py
pyflies/lang/common.py
pyflies/lang/common.tx
pyflies/lang/components.py
pyflies/lang/components.tx
pyflies/lang/pyflies.py
pyflies/lang/pyflies.tx
pyflies/lang/pyflies_processor.py
pyflies-0.5.1.dist-info/LICENSE
pyflies-0.5.1.dist-info/METADATA
pyflies-0.5.1.dist-info/WHEEL
pyflies-0.5.1.dist-info/entry_points.txt
pyflies-0.5.1.dist-info/top_level.txt
pyflies-0.5.1.dist-info/RECORD
